{
    "id": "312b21574d2808bccdce5ec4c13ca415",
    "filename": "CO19_Wet_Dreams.Kunduz",
    "title": "CO19_Wet_Dreams",
    "author": "Unknown",
    "player_count": 19,
    "terrain": "Kunduz",
    "tags": [
        "FIX NEEDED"
    ],
    "overview": "",
    "overview_img": "imgs/default_overview.jpg",
    "briefing": "<h4>I. Обстановка:</h4>Для поддержания лояльного отношения местного населения к силам коалиции, командование решило заключить союзы с крупными общинами Афганистана. Одна из общин обратилась к нам за помощью. Они утверждают, что талибы схватили и удерживают в заложниках старейшину деревни. Таким образом боевики пытаются запугать мирное население и предотвратить сотрудничество местных с ISAF. Наша разведка установила точное местоположение заключенного, он находится в кишлаке Tappeh Tark, расположенном на берегу реки Кундуз. Для спасения заложника выделено два отряда SEAL ВМФ США. <h4>А. Враждебные силы:</h4>Террористы группировки Талибан. Вооружены устаревшим оружием советского и китайского производства. Единой униформы не имеют, одеты в гражданскую одежду. Их численность оценивают во взвод.<h4>Б. Дружественные силы:</h4>Взвод спецназа ВМФ США<h4>II. Задание:</h4>Освободить заложника, удерживаемого в кишлаке Tappeh Tark и доставить его на точку Safehouse<h4>III. Выполнение:</h4>1. Отряд Dagger экипирован для подводных операции и достигнет Tappeh Tark на моторных лодках, после чего проникнет в компаунд через подземные туннели (по информации местных, вход должен быть расположен под водой). 2. Отряд Catapult зачистит местность вокруг кишлака и обеспечит безопасность заложника на пути к Safehouse. <br />3. При потерях, выше допустимых, следуют вернуться на точку Extraction Point<br />4. При гибели заложника рекомендуется вернуться на Extraction Point<h4>IV. Поддержка:</h4>6 моторных лодок для отряда Dagger<h4>V. Сигналы:</h4>PL NET LR CH 50<br />Dagger 1-1 SR CH1<br />Catapult 1-2 SR CH2<br />Командир взвода имеет доступ к нашлемным камерам командиров отрядов.<h4>VI. Замечания:</h4>Powered by 10Dozen technologies<br />Mission idea by Lim&Fly",
    "map_shot": "",
    "mission_date": "Unknown"
}