{
    "id": "09cb28419df3f506055c8d91b3db75f5",
    "filename": "CO2720Operation20Edelweiss.brf_sumava",
    "title": "CO27 Operation Edelweiss",
    "author": "Реневал",
    "player_count": 27,
    "terrain": "brf_sumava",
    "tags": [
        "SPECOPS",
        "INFANTRY",
        "MOUT"
    ],
    "overview": "",
    "overview_img": "imgs/CO2720Operation20Edelweiss.brf_sumava.jpg",
    "briefing": "<h4>I. Обстановка:</h4>В 2022 году между Австрией и Италией вспыхнул вооруженный конфликт из-за территориальный несогласий. Регион стал все более напряженным, и оба государства оказались в состоянии военного положения. Австрия получила поддержку от России и США, которые предоставили значительные поставки припасов и современную военную технику. В ответ на эскалацию Франция поддержала Италию. Последняя провела обширную мобилизацию и готова идти в бой, заручившись поддержкой своего западного соседа.<br /><br />Наш взвод получил задачу по рейду в тыл передовых французский частей и уничтожению передовой базы противника, в настоящий момент мы находимся к западу от вражеского FOB и готовы к штурму.<h4>А. Враждебные силы:</h4>1. До нескольких взводов пехоты, в том числе ПТ<br />2. APC VBCI 1x<h4>Б. Дружественные силы:</h4>1'1-Rifleman 2x, Auto rifleman 2x, Grenadier 2x, SL<br />1'2-Rifleman 2x, Auto rifleman 2x, Grenadier 2x, SL<br />1'3-Rifleman 2x, Auto rifleman 2x, Grenadier 2x, SL<br /><br /><h4>II. Задание:</h4>1. Уничтожить противника в н.п. Maly Bor<br />3. Зачистить военную базу (FOB)<h4>III. Выполнение:</h4>Выдвигаемся техникой и на точку TRP высадка после чего мы должны взять н.п. штурмом и взять военную базу в кольцо а затем захватить ее.<br /><br />Из-за открытого характера местности, используйте технику осторожно. <h4>IV. Поддержка:</h4>1.Dingo (MG3) 3x<br />2.Dingo (MK19) 1x<br />4.M1036 (TOW) 1x<h4>V. Сигналы:</h4>PL NET 50 Mhz<br />SUP NET 51 Mhz<br /><br />1'1 - SR CH 1<br />1'2 - SR CH 2<br />1'3 - SR CH 3<h4>VI. Замечания:</h4>'",
    "map_shot": "",
    "mission_date": "2022"
}