{
    "id": "fc008adaa02051d51e57699c15aea679",
    "filename": "co29-wild-hunt.Woodland_ACR",
    "title": "CO29 The Wild Hunt",
    "author": "Tactical Shift",
    "player_count": 29,
    "terrain": "Woodland_ACR",
    "tags": [],
    "overview": "",
    "overview_img": "imgs/default_overview.jpg",
    "briefing": "<br/><br/>I. Обстановка:<br/>В государстве Bystrica произошел государственный переворот, итогами которого стало принятие новой легитимной власти в лице Верховной Рады. Однако Черноруссия посчитала новую власть не легитимной и начала военное вторжение, которое продлилось около двух лет, пока у Черноруссии под весом санкций не начались проблемы с экономикой.<br />После окончания военного вторжения со стороны Черноруссии, и проведения силовой операции по восстановлению порядка, на территории Bystrica остались очаги сепаратистов, для борьбы с которыми по просьбе легитимной власти было отправлено специальное подразделение CHASER вооруженных сил США.<br /><br />В течении прошлого месяца радиоразведка занималась мониторингом радиочастот и сопоставив их с активностью сепаратистов, и может точно определить местоположение источника сигнала как только ополчение попробует воспользоваться средствами коммуникаций. В то время как задачей CHASER является отлов и уничтожение сепаратистов.<br /><br/><br/>А. Враждебные силы:<br/>Нерегулярные войска ополчения<br />    Численность - неизвестно<br/><br/>Б. Дружественные силы:<br/>Специальные подразделения вооруженных сил США<br />    3 Отряда<br />        CHASER 1'1<br />        CHASER 1'2<br />        CHASER 1'3<br/><br/>II. Задание:<br/>Проследовать по маршруту воздушного патрулирования.<br /><br/><br/>III. Выполнение:<br/>По плану командира<br/><br/>IV. Поддержка:<br/>4 вертолета MH-6<br />1 вертолет UH-60M<br/><br/>V. Сигналы:<br/>PL NET - LR CH 1<br /><br />CHASER 1'1 - SR CH 1<br />CHASER 1'2 - SR CH 2<br />CHASER 1'3 - SR CH 3<br/><br/>VI. Замечания:<br/>СЛЕДУЙТЕ ПО ТОЧКАМ, НЕ ЗАДАВАЙТЕ ВОПРОСЫ, НЕ ПРОВОДИТЕ БРИФИНГ КРОМЕ ЗАЧТЕНИЯ МИССИИ.<br /><br />powered by dzn_dynai, dzn_gear, dzn_tSF",
    "map_shot": "",
    "mission_date": "2016"
}